.gitignore
LICENSE
README.md
py_requirements.nix
pyproject.toml
requirements.txt
setup.cfg
antares_bot/__init__.py
antares_bot/__main__.py
antares_bot/basic_language.py
antares_bot/bot_base.py
antares_bot/bot_default_cfg.py
antares_bot/bot_inst.py
antares_bot/bot_logging.py
antares_bot/bot_method_wrapper.py
antares_bot/bot_method_wrapper.pyi
antares_bot/callback_manager.py
antares_bot/context.py
antares_bot/context_manager.py
antares_bot/error.py
antares_bot/framework.py
antares_bot/init_hooks.py
antares_bot/module_analyze_utils.py
antares_bot/module_base.py
antares_bot/module_loader.py
antares_bot/permission_check.py
antares_bot/test_commands.py
antares_bot/text_process.py
antares_bot/utils.py
antares_bot.egg-info/PKG-INFO
antares_bot.egg-info/SOURCES.txt
antares_bot.egg-info/dependency_links.txt
antares_bot.egg-info/entry_points.txt
antares_bot.egg-info/requires.txt
antares_bot.egg-info/top_level.txt
antares_bot/internal_modules/__init__.py
antares_bot/internal_modules/obj_graph.py
antares_bot/multi_lang/__init__.py
antares_bot/multi_lang/context.py
antares_bot/patching/__init__.py
antares_bot/patching/job_quque_ex.py
antares_bot/sqlite/__init__.py
antares_bot/sqlite/creater.py
antares_bot/sqlite/manager.py
modules/echo.py
modules/timer.py