Metadata-Version: 2.1
Name: antares_bot
Version: 21.4
Summary: A Telegram bot framework wrapping many things.
Home-page: https://github.com/Antares0982/antares-bot
Download-URL: https://github.com/Antares0982/antares-bot
Author: Antares0982
Author-email: Antares <antares@alyr.dev>
Project-URL: Bug Tracker, https://github.com/Antares0982/antares-bot/issues
Project-URL: Source Code, https://github.com/Antares0982/antares-bot
Keywords: python,telegram,bot,api,wrapper
Platform: any
Classifier: Development Status :: 4 - Beta
Classifier: Intended Audience :: Developers
Classifier: License :: OSI Approved :: GNU General Public License v3 (GPLv3)
Classifier: Operating System :: POSIX :: Linux
Classifier: Topic :: Software Development :: Libraries :: Python Modules
Classifier: Topic :: Communications :: Chat
Classifier: Topic :: Internet
Classifier: Programming Language :: Python
Classifier: Programming Language :: Python :: 3
Classifier: Programming Language :: Python :: 3.10
Classifier: Programming Language :: Python :: 3.11
Classifier: Programming Language :: Python :: 3.12
Classifier: Programming Language :: Python :: 3.13
Requires-Python: >=3.10
License-File: LICENSE
Requires-Dist: antares-ptb[job-queue]==v21.4
Requires-Dist: aiosqlite
Requires-Dist: objgraph
Provides-Extra: pika
Requires-Dist: aio-pika; extra == "pika"
